steg/__init__.py
steg/_steg.py
steg/common.py
steg/steg.py
steg/steg_img.py
steg/test.py
steg-0.1.5.dist-info/LICENSE
steg-0.1.5.dist-info/METADATA
steg-0.1.5.dist-info/WHEEL
steg-0.1.5.dist-info/entry_points.txt
steg-0.1.5.dist-info/top_level.txt
steg-0.1.5.dist-info/RECORD
