Metadata-Version: 2.1
Name: steg
Version: 0.1.5
Summary: Steg is a simple python library for hiding and extracting messages from losslessly compressed images using least-significant-bit (LSB) steganography.
Home-page: https://github.com/beatsbears/steg
Author: Andrew Scott
License: MIT License
Platform: UNKNOWN
Requires-Dist: Pillow (==8.1.2)
